{"version":1,"resource":"file:///home/autummata/dev/octonotes/src/components/tool/child/childStates/idle.ts","entries":[{"id":"5ohS.ts","timestamp":1719975105171},{"id":"Myzd.ts","timestamp":1719975172651},{"id":"SN5I.ts","timestamp":1719975221548},{"id":"x3yz.ts","timestamp":1719975368868},{"id":"1S9A.ts","source":"moved.source","sourceDescription":"~/dev/octonotes/src/components/tool/childStates/idle.ts","timestamp":1719975401842},{"id":"SznW.ts","source":"Workspace Edit","timestamp":1719975402631}]}